cli/__init__.py
cli/auth.py
cli/config.py
cli/main.py
cli/utils.py
cli/commands/__init__.py
cli/commands/analyze.py
cli/commands/login.py
cli/commands/upload.py
cli/services/__init__.py
cli/services/analyze_service.py
deepwave_cli-1.0.14.dist-info/licenses/LICENSE
engine/__init__.py
engine/analyze.py
engine/ignore.py
engine/models.py
engine/stats.py
engine/binder/__init__.py
engine/binder/import_graph.py
engine/binder/resolution_strategy.py
engine/binder/symbol_index.py
engine/binder/symbol_resolver.py
engine/bundle/__init__.py
engine/bundle/schema.py
engine/bundle/writer.py
engine/frameworks/base.py
engine/frameworks/detector.py
engine/frameworks/factory.py
engine/frameworks/aspnet/pattern_matcher.py
engine/frameworks/django/filter.py
engine/frameworks/django/mapper.py
engine/frameworks/django/pattern_matcher.py
engine/frameworks/express/pattern_matcher.py
engine/frameworks/fastapi/dependency_resolver.py
engine/frameworks/fastapi/discovery.py
engine/frameworks/fastapi/filter.py
engine/frameworks/fastapi/mapper.py
engine/frameworks/fastapi/node_mapper.py
engine/frameworks/fastapi/pattern_matcher.py
engine/frameworks/fastapi/resolution_strategy.py
engine/frameworks/flask/pattern_matcher.py
engine/frameworks/springboot/pattern_matcher.py
engine/graph/call_graph.py
engine/graph/core_graph.py
engine/graph/extractor.py
engine/parser/__init__.py
engine/parser/base_parser.py
engine/parser/import_analyzer.py
engine/parser/import_info.py
engine/parser/parse_cache.py
engine/parser/query_engine.py
engine/parser/tree_sitter_parser.py
engine/parser/queries/python/__init__.py
engine/parser/queries/python/fastapi/depends.scm
engine/parser/queries/python/generic/assignments.scm
engine/parser/queries/python/generic/calls.scm
engine/parser/queries/python/generic/classes.scm
engine/parser/queries/python/generic/decorators.scm
engine/parser/queries/python/generic/functions.scm
engine/parser/queries/python/generic/imports.scm
deepwave_cli-1.0.14.dist-info/METADATA
deepwave_cli-1.0.14.dist-info/WHEEL
deepwave_cli-1.0.14.dist-info/entry_points.txt
deepwave_cli-1.0.14.dist-info/top_level.txt
deepwave_cli-1.0.14.dist-info/RECORD
