Metadata-Version: 2.4
Name: deepwave-cli
Version: 1.0.14
Summary: Command-line interface for analyzing codebases and uploading results to Deepwave
Author-email: Deepwave <support@deepwave.dev>
License: MIT
Project-URL: Homepage, https://github.com/Deepwave-dev/Deepwave-cli
Keywords: code-analysis,cli,deepwave,static-analysis
Classifier: Development Status :: 4 - Beta
Classifier: Intended Audience :: Developers
Classifier: License :: OSI Approved :: MIT License
Classifier: Programming Language :: Python :: 3
Classifier: Programming Language :: Python :: 3.10
Classifier: Programming Language :: Python :: 3.11
Classifier: Programming Language :: Python :: 3.12
Requires-Python: >=3.10
License-File: LICENSE
Requires-Dist: click>=8.0.0
Requires-Dist: httpx>=0.24.0
Requires-Dist: GitPython>=3.1.0
Requires-Dist: tree-sitter>=0.20.0
Requires-Dist: tree-sitter-python>=0.20.0
Requires-Dist: pydantic>=2.0.0
Requires-Dist: loguru>=0.7.0
Dynamic: license-file
